typetastic/__init__.py
typetastic/bot_handlers.py
typetastic/handler_data.py
typetastic/robot.py
typetastic/session_config.py
typetastic/text_colors.py
typetastic-1.1.8.dist-info/LICENSE
typetastic-1.1.8.dist-info/METADATA
typetastic-1.1.8.dist-info/WHEEL
typetastic-1.1.8.dist-info/top_level.txt
typetastic-1.1.8.dist-info/RECORD
