Metadata-Version: 2.1
Name: typetastic
Version: 1.1.8
Summary: Python tool for building great screencasts, presentations, video tutorials..
Home-page: https://github.com/thisdougb/typetastic
Author: Doug Bridgens
Author-email: typetastic@far-oeuf.com
License: UNKNOWN
Project-URL: Bug Tracker, https://github.com/thisdougb/typetastic/issues
Project-URL: Source Code, https://github.com/thisdougb/typetastic
Keywords: automation screencast videotut
Platform: UNKNOWN
Classifier: Programming Language :: Python :: 3
Classifier: License :: OSI Approved :: GNU General Public License v3 (GPLv3)
Classifier: Operating System :: MacOS :: MacOS X
Classifier: Operating System :: POSIX :: Linux
Classifier: Topic :: Education :: Computer Aided Instruction (CAI)
Requires-Python: >=3.6
Requires-Dist: getch (>=1.0)
Requires-Dist: pexpect (>=4.8.0)
Requires-Dist: PyYAML (>=5.3.1)
